{
  "id": "target-client",
  "clientId": "target-client",
  "name": "target-client",
  "description": "This client represents the target service that will accept the new token.",
  "rootUrl": "",
  "adminUrl": "",
  "baseUrl": "",
  "surrogateAuthRequired": false,
  "enabled": true,
  "alwaysDisplayInConsole": false,
  "clientAuthenticatorType": "client-secret",
  "secret": "jnG1UuQzWgQROtjhU1ku9YlsRsupzL5o",
  "redirectUris": [
    "*"
  ],
  "webOrigins": [],
  "notBefore": 0,
  "bearerOnly": false,
  "consentRequired": false,
  "standardFlowEnabled": true,
  "implicitFlowEnabled": false,
  "directAccessGrantsEnabled": false,
  "serviceAccountsEnabled": false,
  "publicClient": false,
  "frontchannelLogout": true,
  "protocol": "openid-connect",
  "attributes": {
    "realm_client": "false",
    "oidc.ciba.grant.enabled": "false",
    "client.secret.creation.time": "1757927723",
    "backchannel.logout.session.required": "true",
    "standard.token.exchange.enabled": "false",
    "oauth2.device.authorization.grant.enabled": "false",
    "backchannel.logout.revoke.offline.tokens": "false"
  },
  "authenticationFlowBindingOverrides": {},
  "fullScopeAllowed": true,
  "nodeReRegistrationTimeout": -1,
  "defaultClientScopes": [
    "web-origins",
    "acr",
    "profile",
    "roles",
    "basic",
    "email"
  ],
  "optionalClientScopes": [
    "audience-target-scope",
    "address",
    "phone",
    "organization",
    "offline_access",
    "microprofile-jwt"
  ]
}
